hsaquery/__init__.py
hsaquery/demo.py
hsaquery/esa_query.py
hsaquery/fetch.py
hsaquery/fetch_mast.py
hsaquery/overlaps.py
hsaquery/query.py
hsaquery/utils.py
hsaquery/version.py
hsaquery-0.1.8.dist-info/METADATA
hsaquery-0.1.8.dist-info/RECORD
hsaquery-0.1.8.dist-info/WHEEL
hsaquery-0.1.8.dist-info/top_level.txt
