Metadata-Version: 2.1
Name: hsaquery
Version: 0.1.8
Summary: Python tools for querying the ESA Hubble Science Archive
Home-page: https://github.com/gbrammer/esa-hsaquery
Author: Gabriel Brammer
Author-email: gbrammer@gmail.com
License: MIT
Download-URL: https://github.com/gbrammer/esa-hsaquery/tarball/0.1.8
Platform: UNKNOWN
Classifier: Development Status :: 1 - Planning
Classifier: Intended Audience :: Science/Research
Classifier: Topic :: Scientific/Engineering :: Astronomy
